ape_langchain/__init__.py
ape_langchain/chains.py
ape_langchain/schema.py
ape_langchain/tools.py
ape_langchain/utils.py
ape_langchain-1.0.5.dist-info/METADATA
ape_langchain-1.0.5.dist-info/WHEEL
ape_langchain-1.0.5.dist-info/top_level.txt
ape_langchain-1.0.5.dist-info/RECORD
