Metadata-Version: 2.4
Name: ape-langchain
Version: 1.0.5
Summary: LangChain integration for APE (AI Programmatic Execution)
Author-email: David Van Aelst <david@skyrah.be>
License: MIT
Project-URL: Homepage, https://github.com/Quynah/ape-lang
Project-URL: Documentation, https://github.com/Quynah/ape-lang/blob/main/packages/ape-langchain/README.md
Project-URL: Repository, https://github.com/Quynah/ape-lang
Classifier: Development Status :: 3 - Alpha
Classifier: Intended Audience :: Developers
Classifier: License :: OSI Approved :: MIT License
Classifier: Programming Language :: Python :: 3.11
Classifier: Topic :: Software Development :: Libraries
Requires-Python: >=3.11
Requires-Dist: ape-lang>=1.0.4
Requires-Dist: typing-extensions>=4.0.0
Provides-Extra: langchain
Requires-Dist: langchain>=0.1.0; extra == "langchain"
Requires-Dist: langchain-core>=0.1.0; extra == "langchain"
Provides-Extra: dev
Requires-Dist: pytest>=7.0.0; extra == "dev"
Requires-Dist: pytest-cov>=4.0.0; extra == "dev"
Requires-Dist: black>=23.0.0; extra == "dev"
Requires-Dist: mypy>=1.0.0; extra == "dev"
